psr_container/__init__.py
psr_container/container.py
psr_container-1.0.0.dist-info/METADATA
psr_container-1.0.0.dist-info/WHEEL
psr_container-1.0.0.dist-info/RECORD
