Metadata-Version: 2.3
Name: psr-container
Version: 1.0.0
Summary: DI Container Interface
Author: Alexey Volkov
Author-email: webwizardry@hotmail.com
Requires-Python: >=3.12
Classifier: Programming Language :: Python :: 3
Classifier: Programming Language :: Python :: 3.12
Classifier: Programming Language :: Python :: 3.13
